examples/__init__.py
examples/case_study.py
examples/paper.py
examples/plot_load_distribution.py
examples/plot_node_loads.py
examples/plot_workload_distribution.py
examples/tutorial.py
quoracle/__init__.py
quoracle/distribution.py
quoracle/expr.py
quoracle/geometry.py
quoracle/quorum_system.py
quoracle/search.py
quoracle/viz.py
tests/__init__.py
tests/test_expr.py
tests/test_geometry.py
tests/test_quorum_system.py
tests/test_search.py
tests/test_strategy.py
quoracle-0.0.4.dist-info/LICENSE
quoracle-0.0.4.dist-info/METADATA
quoracle-0.0.4.dist-info/WHEEL
quoracle-0.0.4.dist-info/top_level.txt
quoracle-0.0.4.dist-info/RECORD
