Metadata-Version: 2.1
Name: quoracle
Version: 0.0.4
Summary: A library for modelling, analyzing, and optimizing quorum systems
Home-page: https://github.com/mwhittaker/quorums
Author: Michael Whittaker
Author-email: mwhittttaker@gmail.com
License: UNKNOWN
Platform: UNKNOWN
Classifier: Programming Language :: Python :: 3
Classifier: License :: OSI Approved :: MIT License
Classifier: Operating System :: OS Independent
Requires-Python: >=3.8
License-File: LICENSE
Requires-Dist: matplotlib
Requires-Dist: pulp
